pingpad/__init__.py
PingPad-0.0.1.dist-info/LICENSE
PingPad-0.0.1.dist-info/METADATA
PingPad-0.0.1.dist-info/WHEEL
PingPad-0.0.1.dist-info/top_level.txt
PingPad-0.0.1.dist-info/RECORD
